requirements.txt
setup.py
django_vote_base/__init__.py
django_vote_base/models.py
django_vote_base/views.py
django_vote_base.egg-info/PKG-INFO
django_vote_base.egg-info/SOURCES.txt
django_vote_base.egg-info/dependency_links.txt
django_vote_base.egg-info/requires.txt
django_vote_base.egg-info/top_level.txt