Metadata-Version: 2.1
Name: django-vote-base
Version: 2020.7.1
Summary: Django vote base models and views
Home-page: https://github.com/andrewp-as-is/django-vote-base.py
License: Unlicense
Keywords: django vote
Platform: UNKNOWN
Classifier: Framework :: Django
Classifier: License :: Public Domain
Classifier: Operating System :: OS Independent
Classifier: Programming Language :: Python :: 3
